sql_backup/__init__.py
sql_backup/__main__.py
sql_backup/backup.py
sql_backup/config.py
sql_backup/config_validator.py
sql_backup/logger.py
sql_backup/main.py
sql_backup/notifications.py
sql_backup/remote_upload.py
sqlbackup-0.2.2.dist-info/licenses/LICENSE
tests/__init__.py
tests/run_tests.py
tests/test_backup.py
tests/test_config.py
tests/test_config_validator.py
tests/test_logger.py
tests/test_notification.py
tests/test_notifications.py
tests/test_remote_upload.py
sqlbackup-0.2.2.dist-info/METADATA
sqlbackup-0.2.2.dist-info/WHEEL
sqlbackup-0.2.2.dist-info/entry_points.txt
sqlbackup-0.2.2.dist-info/top_level.txt
sqlbackup-0.2.2.dist-info/RECORD
