Metadata-Version: 2.4
Name: sqlBackup
Version: 0.2.2
Summary: A modern Python-based backup tool for MySQL databases
Home-page: https://github.com/klevze/sqlBackup
Author: Gregor
Author-email: gregor@klevze.com
Project-URL: Bug Reports, https://github.com/klevze/sqlBackup/issues
Project-URL: Source, https://github.com/klevze/sqlBackup
Project-URL: Documentation, https://github.com/klevze/sqlBackup#readme
Keywords: mysql backup database dump archive notification sftp ftp telegram email slack sms
Classifier: Development Status :: 4 - Beta
Classifier: Environment :: Console
Classifier: Intended Audience :: System Administrators
Classifier: Intended Audience :: Developers
Classifier: Operating System :: OS Independent
Classifier: Programming Language :: Python :: 3
Classifier: Programming Language :: Python :: 3.6
Classifier: Programming Language :: Python :: 3.7
Classifier: Programming Language :: Python :: 3.8
Classifier: Programming Language :: Python :: 3.9
Classifier: Programming Language :: Python :: 3.10
Classifier: Programming Language :: Python :: 3.11
Classifier: Topic :: Database
Classifier: Topic :: System :: Archiving :: Backup
Classifier: Topic :: System :: Systems Administration
Classifier: Topic :: Utilities
Requires-Python: >=3.6
License-File: LICENSE
Requires-Dist: requests>=2.25.0
Requires-Dist: paramiko>=2.7.0
Requires-Dist: twilio>=7.0.0
Dynamic: author
Dynamic: author-email
Dynamic: classifier
Dynamic: description
Dynamic: description-content-type
Dynamic: home-page
Dynamic: keywords
Dynamic: license-file
Dynamic: project-url
Dynamic: requires-dist
Dynamic: requires-python
Dynamic: summary
